tomodoro/__init__.py
tomodoro/ascii_numbers.py
tomodoro/colors.py
tomodoro/main.py
tomodoro/tui_elements.py
tomodoro-0.1.3.dist-info/METADATA
tomodoro-0.1.3.dist-info/WHEEL
tomodoro-0.1.3.dist-info/entry_points.txt
tomodoro-0.1.3.dist-info/licenses/LICENSE
tomodoro-0.1.3.dist-info/RECORD
