Metadata-Version: 2.4
Name: tomodoro
Version: 0.1.3
Summary: A TUI pomodoro timer with no dependencies.
Project-URL: Source, https://github.com/jdhalbert/tomodoro
Author-email: jdhalbert <tomodoro@rmdir.dev>
License: MIT
License-File: LICENSE
Requires-Python: >=3.13
